nemollm/__init__.py
nemollm/api.py
nemollm/cli.py
nemollm/error.py
nemollm/version.py
nemollm-0.3.5.dist-info/METADATA
nemollm-0.3.5.dist-info/WHEEL
nemollm-0.3.5.dist-info/entry_points.txt
nemollm-0.3.5.dist-info/top_level.txt
nemollm-0.3.5.dist-info/RECORD
