Metadata-Version: 2.1
Name: nemollm
Version: 0.3.5
Summary: Python client library for the NeMo LLM API
Home-page: https://pypi.org/project/nemollm
Author: NVIDIA NeMo LLM
Author-email: nvidia-nemollm@nvidia.com
License: UNKNOWN
Platform: UNKNOWN
Requires-Python: >=3.6
Requires-Dist: python-dateutil (>=2.5.3)
Requires-Dist: urllib3 (>=1.25.3)
Requires-Dist: requests-futures
Requires-Dist: requests-toolbelt
Requires-Dist: tqdm
Requires-Dist: typing-extensions
